HELP.md
MANIFEST.in
README.rst
bottle.py
manage
setup.cfg
setup.py
database/zodb.conf
database/blobs/keep_me.txt
drink/__init__.py
drink/config.py
drink/migration.py
drink/renames.py
drink/settings.ini
drink/types.py
drink/zdb.py
drink.egg-info/PKG-INFO
drink.egg-info/SOURCES.txt
drink.egg-info/dependency_links.txt
drink.egg-info/entry_points.txt
drink.egg-info/not-zip-safe
drink.egg-info/requires.txt
drink.egg-info/top_level.txt
drink/objects/__init__.py
drink/objects/filesystem.py
drink/objects/finder.py
drink/objects/generic.py
drink/objects/markdown.py
drink/objects/tasks.py
drink/objects/users.py
drink/static/back.png
drink/static/fileuploader.js
drink/static/fullcalendar.css
drink/static/fullcalendar.min.js
drink/static/jquery-1.5.js
drink/static/jquery-1.5.min.js
drink/static/jquery-ui-1.8.custom.min.js
drink/static/jquery.dataSelector.js
drink/static/jquery.validate.min.js
drink/static/listing.js
drink/static/loading.gif
drink/static/main.js
drink/static/page.css
drink/static/pygments.css
drink/static/tasks.js
drink/static/actions/back.png
drink/static/actions/close.png
drink/static/actions/delete.png
drink/static/actions/download.png
drink/static/actions/edit.png
drink/static/actions/exit.png
drink/static/actions/find.png
drink/static/actions/home.png
drink/static/actions/logout.png
drink/static/actions/new.png
drink/static/actions/open.png
drink/static/actions/personal.png
drink/static/actions/top.png
drink/static/actions/undo.png
drink/static/actions/upload.png
drink/static/actions/view.png
drink/static/markitup/jquery.markitup.js
drink/static/markitup/sets/markdown/set.js
drink/static/markitup/sets/markdown/style.css
drink/static/markitup/sets/markdown/images/bold.png
drink/static/markitup/sets/markdown/images/clean.png
drink/static/markitup/sets/markdown/images/code.png
drink/static/markitup/sets/markdown/images/deindent.png
drink/static/markitup/sets/markdown/images/h1.png
drink/static/markitup/sets/markdown/images/h2.png
drink/static/markitup/sets/markdown/images/h3.png
drink/static/markitup/sets/markdown/images/h4.png
drink/static/markitup/sets/markdown/images/h5.png
drink/static/markitup/sets/markdown/images/h6.png
