Metadata-Version: 1.0
Name: drink
Version: 0.0.10
Summary: High-level Web Object-managing framework on top of ZODB and Jinja2
Home-page: UNKNOWN
Author: Fabien Devaux
Author-email: fdev31@gmail.com
License: GPL
Platform: UNKNOWN
